config.toml.example
fasjson_client/__init__.py
fasjson_client/cli/__init__.py
fasjson_client/cli/get_cert.py
fasjson_client/client.py
fasjson_client/config.py
fasjson_client/errors.py
fasjson_client/formats.py
fasjson_client/gss_http.py
fasjson_client/response.py
fasjson_client/tests/__init__.py
fasjson_client/tests/unit/__init__.py
fasjson_client/tests/unit/conftest.py
fasjson_client/tests/unit/fixtures/cert-1.crt
fasjson_client/tests/unit/fixtures/cert-2.crt
fasjson_client/tests/unit/fixtures/cert-3.crt
fasjson_client/tests/unit/fixtures/cert-4.crt
fasjson_client/tests/unit/fixtures/private.key
fasjson_client/tests/unit/fixtures/spec.json
fasjson_client/tests/unit/test_cli.py
fasjson_client/tests/unit/test_cli_get_cert.py
fasjson_client/tests/unit/test_client.py
fasjson_client/tests/unit/test_client_api.py
fasjson_client/tests/unit/test_client_errors.py
fasjson_client/tests/unit/test_config.py
fasjson_client/tests/unit/test_gss_http.py
fasjson_client/tests/unit/test_response.py
fasjson_client/tests/unit/utils.py
tox.ini
fasjson_client-1.1.0.dist-info/LICENSE
fasjson_client-1.1.0.dist-info/METADATA
fasjson_client-1.1.0.dist-info/WHEEL
fasjson_client-1.1.0.dist-info/entry_points.txt
fasjson_client-1.1.0.dist-info/RECORD
