Metadata-Version: 2.1
Name: fasjson-client
Version: 1.1.0
Summary: An OpenAPI client for FASJSON
Home-page: https://github.com/fedora-infra/fasjson-client
License: LGPL-3.0-or-later
Keywords: security
Author: Fedora Infrastructure
Author-email: infrastructure@lists.fedoraproject.org
Requires-Python: >=3.8.0,<4.0.0
Classifier: Development Status :: 4 - Beta
Classifier: Intended Audience :: Developers
Classifier: License :: OSI Approved :: GNU Lesser General Public License v3 or later (LGPLv3+)
Classifier: Programming Language :: Python :: 3
Classifier: Programming Language :: Python :: 3.8
Classifier: Programming Language :: Python :: 3.9
Classifier: Programming Language :: Python :: 3.10
Classifier: Programming Language :: Python :: 3.11
Classifier: Programming Language :: Python :: 3.12
Classifier: Programming Language :: Python :: 3.6
Classifier: Programming Language :: Python :: 3.7
Classifier: Topic :: Security
Classifier: Topic :: Software Development :: Libraries :: Python Modules
Provides-Extra: cli
Requires-Dist: bravado (>=10.6.0,<12)
Requires-Dist: click (>=6.7,<9) ; extra == "cli"
Requires-Dist: cryptography (>=2.3) ; extra == "cli"
Requires-Dist: gssapi (>=1.5.1,<2.0.0)
Requires-Dist: requests (>=2.20.0,<3.0.0)
Requires-Dist: requests-gssapi (>=1.2.1,<2.0.0)
Requires-Dist: tomli ; python_version < "3.11"
Project-URL: Repository, https://github.com/fedora-infra/fasjson-client
